<ForceField>
  <Info>
    <DateGenerated>2022-04-01</DateGenerated>
  </Info>
  <Residues>
    <Residue name="SAM">
      <Atom name="N" type="n3" charge="-0.8818"/>
      <Atom name="CA" type="c3" charge="0.0655"/>
      <Atom name="C" type="c" charge="0.8646"/>
      <Atom name="O" type="o" charge="-0.7313"/>
      <Atom name="CB" type="c3" charge="-0.0564"/>
      <Atom name="CG" type="c3" charge="-0.0891"/>
      <Atom name="SD" type="s4" charge="0.2761"/>
      <Atom name="CE" type="c3" charge="-0.1498"/>
      <Atom name="C5'" type="c3" charge="-0.1641"/>
      <Atom name="C4'" type="c3" charge="0.1651"/>
      <Atom name="O4'" type="os" charge="-0.4326"/>
      <Atom name="C3'" type="c3" charge="0.0821"/>
      <Atom name="O3'" type="oh" charge="-0.5898"/>
      <Atom name="C2'" type="c3" charge="0.0831"/>
      <Atom name="O2'" type="oh" charge="-0.5728"/>
      <Atom name="C1'" type="c3" charge="0.2308"/>
      <Atom name="OXT" type="o" charge="-0.7313"/>
      <Atom name="N1" type="nb" charge="-0.793"/>
      <Atom name="C2" type="ca" charge="0.6909"/>
      <Atom name="N3" type="nb" charge="-0.738"/>
      <Atom name="C4" type="ca" charge="0.4628"/>
      <Atom name="C5" type="ca" charge="-0.2342"/>
      <Atom name="C6" type="ca" charge="0.7622"/>
      <Atom name="N6" type="nh" charge="-0.9545"/>
      <Atom name="N7" type="nc" charge="-0.5431"/>
      <Atom name="C8" type="cd" charge="0.4047"/>
      <Atom name="N9" type="na" charge="-0.291"/>
      <Atom name="H01" type="hn" charge="0.3603"/>
      <Atom name="H02" type="hn" charge="0.3603"/>
      <Atom name="H03" type="h1" charge="0.0817"/>
      <Atom name="H04" type="hc" charge="0.0622"/>
      <Atom name="H05" type="hc" charge="0.0622"/>
      <Atom name="H06" type="h1" charge="0.1012"/>
      <Atom name="H07" type="h1" charge="0.1012"/>
      <Atom name="H08" type="h1" charge="0.091033"/>
      <Atom name="H09" type="h1" charge="0.091033"/>
      <Atom name="H10" type="h1" charge="0.091033"/>
      <Atom name="H11" type="h1" charge="0.0917"/>
      <Atom name="H12" type="h1" charge="0.0917"/>
      <Atom name="H13" type="h1" charge="0.1077"/>
      <Atom name="H14" type="h1" charge="0.0687"/>
      <Atom name="H15" type="ho" charge="0.423"/>
      <Atom name="H16" type="h1" charge="0.1287"/>
      <Atom name="H17" type="ho" charge="0.417"/>
      <Atom name="H18" type="h2" charge="0.1077"/>
      <Atom name="H19" type="h5" charge="0.0551"/>
      <Atom name="H20" type="hn" charge="0.4483"/>
      <Atom name="H21" type="hn" charge="0.4483"/>
      <Atom name="H22" type="h5" charge="0.0758"/>
      <Bond atomName1="N" atomName2="CA"/>
      <Bond atomName1="N" atomName2="H01"/>
      <Bond atomName1="N" atomName2="H02"/>
      <Bond atomName1="CA" atomName2="C"/>
      <Bond atomName1="CA" atomName2="CB"/>
      <Bond atomName1="CA" atomName2="H03"/>
      <Bond atomName1="C" atomName2="O"/>
      <Bond atomName1="C" atomName2="OXT"/>
      <Bond atomName1="CB" atomName2="CG"/>
      <Bond atomName1="CB" atomName2="H04"/>
      <Bond atomName1="CB" atomName2="H05"/>
      <Bond atomName1="CG" atomName2="SD"/>
      <Bond atomName1="CG" atomName2="H06"/>
      <Bond atomName1="CG" atomName2="H07"/>
      <Bond atomName1="SD" atomName2="CE"/>
      <Bond atomName1="SD" atomName2="C5'"/>
      <Bond atomName1="CE" atomName2="H08"/>
      <Bond atomName1="CE" atomName2="H09"/>
      <Bond atomName1="CE" atomName2="H10"/>
      <Bond atomName1="C5'" atomName2="C4'"/>
      <Bond atomName1="C5'" atomName2="H11"/>
      <Bond atomName1="C5'" atomName2="H12"/>
      <Bond atomName1="C4'" atomName2="O4'"/>
      <Bond atomName1="C4'" atomName2="C3'"/>
      <Bond atomName1="C4'" atomName2="H13"/>
      <Bond atomName1="O4'" atomName2="C1'"/>
      <Bond atomName1="C3'" atomName2="O3'"/>
      <Bond atomName1="C3'" atomName2="C2'"/>
      <Bond atomName1="C3'" atomName2="H14"/>
      <Bond atomName1="O3'" atomName2="H15"/>
      <Bond atomName1="C2'" atomName2="O2'"/>
      <Bond atomName1="C2'" atomName2="C1'"/>
      <Bond atomName1="C2'" atomName2="H16"/>
      <Bond atomName1="O2'" atomName2="H17"/>
      <Bond atomName1="C1'" atomName2="N9"/>
      <Bond atomName1="C1'" atomName2="H18"/>
      <Bond atomName1="N1" atomName2="C2"/>
      <Bond atomName1="N1" atomName2="C6"/>
      <Bond atomName1="C2" atomName2="N3"/>
      <Bond atomName1="C2" atomName2="H19"/>
      <Bond atomName1="N3" atomName2="C4"/>
      <Bond atomName1="C4" atomName2="C5"/>
      <Bond atomName1="C4" atomName2="N9"/>
      <Bond atomName1="C5" atomName2="C6"/>
      <Bond atomName1="C5" atomName2="N7"/>
      <Bond atomName1="C6" atomName2="N6"/>
      <Bond atomName1="N6" atomName2="H20"/>
      <Bond atomName1="N6" atomName2="H21"/>
      <Bond atomName1="N7" atomName2="C8"/>
      <Bond atomName1="C8" atomName2="N9"/>
      <Bond atomName1="C8" atomName2="H22"/>
    </Residue>
  </Residues>
  <HarmonicBondForce>
    <Bond type1="c3" type2="n3" length="0.14650000000000002" k="272713.11999999994"/>
    <Bond type1="hn" type2="n3" length="0.10189999999999999" k="328360.3199999999"/>
    <Bond type1="c" type2="c3" length="0.1524" k="261918.39999999994"/>
    <Bond type1="c3" type2="c3" length="0.15380000000000002" k="251793.11999999994"/>
    <Bond type1="c3" type2="h1" length="0.1097" k="276646.07999999996"/>
    <Bond type1="c" type2="o" length="0.1218" k="533627.36"/>
    <Bond type1="c3" type2="hc" length="0.1097" k="276646.07999999996"/>
    <Bond type1="c3" type2="s4" length="0.1831" k="184598.07999999996"/>
    <Bond type1="c3" type2="os" length="0.1432" k="258236.47999999998"/>
    <Bond type1="c3" type2="oh" length="0.1423" k="265014.55999999994"/>
    <Bond type1="ho" type2="oh" length="0.0973" k="310787.5199999999"/>
    <Bond type1="c3" type2="na" length="0.1463" k="274219.3599999999"/>
    <Bond type1="c3" type2="h2" length="0.10960000000000002" k="277566.55999999994"/>
    <Bond type1="ca" type2="nb" length="0.1339" k="408358.3999999999"/>
    <Bond type1="ca" type2="h5" length="0.10880000000000001" k="287189.75999999995"/>
    <Bond type1="ca" type2="ca" length="0.1398" k="385848.4799999999"/>
    <Bond type1="ca" type2="na" length="0.1384" k="351874.3999999999"/>
    <Bond type1="ca" type2="nc" length="0.13520000000000001" k="391371.3599999999"/>
    <Bond type1="ca" type2="nh" length="0.1386" k="349698.7199999999"/>
    <Bond type1="hn" type2="nh" length="0.10120000000000001" k="338569.27999999997"/>
    <Bond type1="cd" type2="nc" length="0.1317" k="439654.7199999999"/>
    <Bond type1="cd" type2="na" length="0.13799999999999998" k="356309.43999999994"/>
    <Bond type1="cd" type2="h5" length="0.10820000000000002" k="294386.23999999993"/>
  </HarmonicBondForce>
  <HarmonicAngleForce>
    <Angle type1="c" type2="c3" type3="n3" angle="1.939758930666498" k="554.7984"/>
    <Angle type1="c3" type2="c3" type3="n3" angle="1.9380136014145037" k="552.288"/>
    <Angle type1="h1" type2="c3" type3="n3" angle="1.9177677820913692" k="414.216"/>
    <Angle type1="c3" type2="n3" type3="hn" angle="1.9074703395046029" k="396.6432"/>
    <Angle type1="c3" type2="c" type3="o" angle="2.150245638457014" k="564.0032000000001"/>
    <Angle type1="c3" type2="c3" type3="c3" angle="1.946216648898877" k="526.3472"/>
    <Angle type1="c3" type2="c3" type3="hc" angle="1.9163715186897738" k="387.4384"/>
    <Angle type1="c" type2="c3" type3="c3" angle="1.9380136014145037" k="529.6944"/>
    <Angle type1="c" type2="c3" type3="h1" angle="1.8887953165082634" k="393.296"/>
    <Angle type1="o" type2="c" type3="o" angle="2.2732913507226145" k="651.8672"/>
    <Angle type1="c3" type2="c3" type3="h1" angle="1.9121827284849875" k="388.2752"/>
    <Angle type1="c3" type2="c3" type3="s4" angle="1.9219565722961558" k="514.6320000000001"/>
    <Angle type1="c3" type2="s4" type3="c3" angle="1.6776104770169495" k="514.6320000000001"/>
    <Angle type1="h1" type2="c3" type3="s4" angle="1.8835593287522805" k="355.64"/>
    <Angle type1="c3" type2="c3" type3="os" angle="1.8844319933782776" k="569.024"/>
    <Angle type1="c3" type2="os" type3="c3" angle="1.9631463426432219" k="524.6736000000001"/>
    <Angle type1="c3" type2="c3" type3="oh" angle="1.9231783027725518" k="564.84"/>
    <Angle type1="h1" type2="c3" type3="os" angle="1.916022452839375" k="425.0944"/>
    <Angle type1="na" type2="c3" type3="os" angle="1.9029324834494175" k="596.6384"/>
    <Angle type1="h2" type2="c3" type3="os" angle="1.9125317943353863" k="425.9312"/>
    <Angle type1="c3" type2="oh" type3="ho" angle="1.872040155689118" k="396.6432"/>
    <Angle type1="h1" type2="c3" type3="oh" angle="1.924400033248948" k="425.9312"/>
    <Angle type1="c3" type2="c3" type3="na" angle="1.9701276596511992" k="548.104"/>
    <Angle type1="c3" type2="c3" type3="h2" angle="1.92370190154815" k="386.6016"/>
    <Angle type1="c3" type2="na" type3="ca" angle="2.170491457780148" k="521.3264"/>
    <Angle type1="c3" type2="na" type3="cd" angle="2.207143372072029" k="517.9792"/>
    <Angle type1="nb" type2="ca" type3="nb" angle="2.2211060060879837" k="593.2912000000001"/>
    <Angle type1="h5" type2="ca" type3="nb" angle="2.0214403396598324" k="434.2992"/>
    <Angle type1="ca" type2="ca" type3="nb" angle="2.145707782401829" k="575.7184"/>
    <Angle type1="nb" type2="ca" type3="nh" angle="2.040988027282169" k="608.3536"/>
    <Angle type1="ca" type2="nb" type3="ca" angle="2.0458749491877533" k="571.5344"/>
    <Angle type1="na" type2="ca" type3="nb" angle="2.2181389463595935" k="584.0864"/>
    <Angle type1="ca" type2="ca" type3="ca" angle="2.094744168243594" k="557.3088"/>
    <Angle type1="ca" type2="ca" type3="nc" angle="2.0895081804876114" k="581.576"/>
    <Angle type1="ca" type2="na" type3="cd" angle="1.974840048631584" k="564.0032000000001"/>
    <Angle type1="ca" type2="ca" type3="na" angle="2.06542263681009" k="578.2288"/>
    <Angle type1="ca" type2="ca" type3="nh" angle="2.1109757302871417" k="571.5344"/>
    <Angle type1="ca" type2="nc" type3="cd" angle="1.8305013194916528" k="606.6800000000001"/>
    <Angle type1="ca" type2="nh" type3="hn" angle="2.0258036627898184" k="405.01120000000003"/>
    <Angle type1="na" type2="cd" type3="nc" angle="1.9586084865880367" k="626.7632000000001"/>
    <Angle type1="h5" type2="cd" type3="nc" angle="2.1907372771032825" k="423.42080000000004"/>
    <Angle type1="h2" type2="c3" type3="na" angle="1.872912820315115" k="420.07360000000006"/>
    <Angle type1="h5" type2="cd" type3="na" angle="2.1214477057991075" k="415.05280000000005"/>
    <Angle type1="hn" type2="n3" type3="hn" angle="1.8570303241219668" k="346.4352"/>
    <Angle type1="hc" type2="c3" type3="hc" angle="1.8776252092954997" k="329.6992"/>
    <Angle type1="h1" type2="c3" type3="h1" angle="1.8929841067130497" k="328.02560000000005"/>
    <Angle type1="hn" type2="nh" type3="hn" angle="2.0092230348958724" k="335.5568"/>
  </HarmonicAngleForce>
  <PeriodicTorsionForce>
    <Proper type1="o" type2="c" type3="c3" type4="n3" periodicity1="2" phase1="3.141592653589793" k1="0.0"/>
    <Proper type1="c3" type2="c3" type3="c3" type4="n3" periodicity1="3" phase1="0.0" k1="0.6508444444444444"/>
    <Proper type1="hc" type2="c3" type3="c3" type4="n3" periodicity1="3" phase1="0.0" k1="0.6508444444444444"/>
    <Proper type1="c3" type2="c3" type3="c3" type4="s4" periodicity1="3" phase1="0.0" k1="0.6508444444444444"/>
    <Proper type1="c3" type2="c3" type3="c3" type4="h1" periodicity1="3" phase1="0.0" k1="0.6508444444444444"/>
    <Proper type1="c" type2="c3" type3="n3" type4="hn" periodicity1="3" phase1="0.0" k1="1.2552"/>
    <Proper type1="c" type2="c3" type3="c3" type4="c3" periodicity1="3" phase1="0.0" k1="0.6508444444444444"/>
    <Proper type1="c" type2="c3" type3="c3" type4="hc" periodicity1="3" phase1="0.0" k1="0.6508444444444444"/>
    <Proper type1="o" type2="c" type3="c3" type4="c3" periodicity1="2" phase1="3.141592653589793" k1="0.0"/>
    <Proper type1="o" type2="c" type3="c3" type4="h1" periodicity1="1" phase1="0.0" k1="3.3472000000000004" periodicity2="2" phase2="0.0" k2="0.0" periodicity3="3" phase3="3.141592653589793" k3="0.33472"/>
    <Proper type1="c3" type2="c3" type3="n3" type4="hn" periodicity1="3" phase1="0.0" k1="1.2552"/>
    <Proper type1="c3" type2="c3" type3="s4" type4="c3" periodicity1="3" phase1="0.0" k1="0.8368"/>
    <Proper type1="h1" type2="c3" type3="s4" type4="c3" periodicity1="3" phase1="0.0" k1="0.8368"/>
    <Proper type1="hc" type2="c3" type3="c3" type4="s4" periodicity1="3" phase1="0.0" k1="0.6508444444444444"/>
    <Proper type1="os" type2="c3" type3="c3" type4="s4" periodicity1="3" phase1="0.0" k1="0.6508444444444444"/>
    <Proper type1="h1" type2="c3" type3="c3" type4="s4" periodicity1="3" phase1="0.0" k1="0.6508444444444444"/>
    <Proper type1="c3" type2="c3" type3="os" type4="c3" periodicity1="3" phase1="0.0" k1="1.6024720000000001" periodicity2="2" phase2="3.141592653589793" k2="0.41840000000000005"/>
    <Proper type1="c3" type2="c3" type3="c3" type4="oh" periodicity1="3" phase1="0.0" k1="0.6508444444444444"/>
    <Proper type1="c3" type2="c3" type3="c3" type4="c3" periodicity1="3" phase1="0.0" k1="0.75312" periodicity2="2" phase2="3.141592653589793" k2="1.046" periodicity3="1" phase3="3.141592653589793" k3="0.8368000000000001"/>
    <Proper type1="na" type2="c3" type3="os" type4="c3" periodicity1="3" phase1="0.0" k1="1.6024720000000001" periodicity2="2" phase2="0.0" k2="2.7196000000000002"/>
    <Proper type1="h2" type2="c3" type3="os" type4="c3" periodicity1="3" phase1="0.0" k1="1.6038666666666666"/>
    <Proper type1="c3" type2="c3" type3="oh" type4="ho" periodicity1="3" phase1="0.0" k1="0.66944" periodicity2="1" phase2="0.0" k2="1.046"/>
    <Proper type1="h1" type2="c3" type3="c3" type4="os" periodicity1="3" phase1="0.0" k1="0.0" periodicity2="1" phase2="0.0" k2="1.046"/>
    <Proper type1="oh" type2="c3" type3="c3" type4="os" periodicity1="3" phase1="0.0" k1="0.602496" periodicity2="2" phase2="0.0" k2="4.916200000000001"/>
    <Proper type1="c3" type2="c3" type3="c3" type4="os" periodicity1="3" phase1="0.0" k1="0.6508444444444444"/>
    <Proper type1="os" type2="c3" type3="na" type4="ca" periodicity1="2" phase1="0.0" k1="0.0"/>
    <Proper type1="os" type2="c3" type3="na" type4="cd" periodicity1="2" phase1="0.0" k1="0.0"/>
    <Proper type1="c3" type2="c3" type3="c3" type4="na" periodicity1="3" phase1="0.0" k1="0.6508444444444444"/>
    <Proper type1="c3" type2="c3" type3="c3" type4="h2" periodicity1="3" phase1="0.0" k1="0.6508444444444444"/>
    <Proper type1="h1" type2="c3" type3="c3" type4="oh" periodicity1="3" phase1="0.0" k1="0.0" periodicity2="1" phase2="0.0" k2="1.046"/>
    <Proper type1="oh" type2="c3" type3="c3" type4="oh" periodicity1="3" phase1="0.0" k1="0.602496" periodicity2="2" phase2="0.0" k2="4.916200000000001"/>
    <Proper type1="c3" type2="c3" type3="na" type4="ca" periodicity1="2" phase1="0.0" k1="0.0"/>
    <Proper type1="c3" type2="c3" type3="na" type4="cd" periodicity1="2" phase1="0.0" k1="0.0"/>
    <Proper type1="na" type2="c3" type3="c3" type4="oh" periodicity1="3" phase1="0.0" k1="0.6508444444444444"/>
    <Proper type1="h2" type2="c3" type3="c3" type4="oh" periodicity1="3" phase1="0.0" k1="0.6508444444444444"/>
    <Proper type1="h1" type2="c3" type3="os" type4="c3" periodicity1="3" phase1="0.0" k1="1.6038666666666666"/>
    <Proper type1="nb" type2="ca" type3="na" type4="c3" periodicity1="2" phase1="3.141592653589793" k1="1.2552"/>
    <Proper type1="ca" type2="ca" type3="na" type4="c3" periodicity1="2" phase1="3.141592653589793" k1="1.2552"/>
    <Proper type1="nc" type2="cd" type3="na" type4="c3" periodicity1="2" phase1="3.141592653589793" k1="7.1128"/>
    <Proper type1="h5" type2="cd" type3="na" type4="c3" periodicity1="2" phase1="3.141592653589793" k1="7.1128"/>
    <Proper type1="nb" type2="ca" type3="nb" type4="ca" periodicity1="2" phase1="3.141592653589793" k1="20.0832"/>
    <Proper type1="ca" type2="ca" type3="ca" type4="nb" periodicity1="2" phase1="3.141592653589793" k1="15.167"/>
    <Proper type1="nb" type2="ca" type3="ca" type4="nc" periodicity1="2" phase1="3.141592653589793" k1="15.167"/>
    <Proper type1="nb" type2="ca" type3="nh" type4="hn" periodicity1="2" phase1="3.141592653589793" k1="4.3932"/>
    <Proper type1="ca" type2="ca" type3="nb" type4="ca" periodicity1="2" phase1="3.141592653589793" k1="20.0832"/>
    <Proper type1="nh" type2="ca" type3="nb" type4="ca" periodicity1="2" phase1="3.141592653589793" k1="20.0832"/>
    <Proper type1="na" type2="ca" type3="nb" type4="ca" periodicity1="2" phase1="3.141592653589793" k1="20.0832"/>
    <Proper type1="nb" type2="ca" type3="na" type4="cd" periodicity1="2" phase1="3.141592653589793" k1="1.2552"/>
    <Proper type1="h5" type2="ca" type3="nb" type4="ca" periodicity1="2" phase1="3.141592653589793" k1="20.0832"/>
    <Proper type1="ca" type2="ca" type3="ca" type4="nh" periodicity1="2" phase1="3.141592653589793" k1="15.167"/>
    <Proper type1="ca" type2="ca" type3="nc" type4="cd" periodicity1="2" phase1="3.141592653589793" k1="20.0832"/>
    <Proper type1="h2" type2="c3" type3="na" type4="ca" periodicity1="2" phase1="0.0" k1="0.0"/>
    <Proper type1="nc" type2="cd" type3="na" type4="ca" periodicity1="2" phase1="3.141592653589793" k1="7.1128"/>
    <Proper type1="h5" type2="cd" type3="na" type4="ca" periodicity1="2" phase1="3.141592653589793" k1="7.1128"/>
    <Proper type1="ca" type2="ca" type3="na" type4="cd" periodicity1="2" phase1="3.141592653589793" k1="1.2552"/>
    <Proper type1="ca" type2="ca" type3="nh" type4="hn" periodicity1="2" phase1="3.141592653589793" k1="4.3932"/>
    <Proper type1="na" type2="cd" type3="nc" type4="ca" periodicity1="2" phase1="3.141592653589793" k1="19.874000000000002"/>
    <Proper type1="h5" type2="cd" type3="nc" type4="ca" periodicity1="2" phase1="3.141592653589793" k1="19.874000000000002"/>
    <Proper type1="ca" type2="ca" type3="ca" type4="na" periodicity1="2" phase1="3.141592653589793" k1="15.167"/>
    <Proper type1="nc" type2="ca" type3="ca" type4="nh" periodicity1="2" phase1="3.141592653589793" k1="15.167"/>
    <Proper type1="na" type2="ca" type3="ca" type4="nc" periodicity1="2" phase1="3.141592653589793" k1="15.167"/>
    <Proper type1="h2" type2="c3" type3="na" type4="cd" periodicity1="2" phase1="0.0" k1="0.0"/>
    <Proper type1="h1" type2="c3" type3="c3" type4="na" periodicity1="3" phase1="0.0" k1="0.6508444444444444"/>
    <Proper type1="h1" type2="c3" type3="n3" type4="hn" periodicity1="3" phase1="0.0" k1="1.2552"/>
    <Proper type1="h1" type2="c3" type3="c3" type4="hc" periodicity1="3" phase1="0.0" k1="0.6508444444444444"/>
    <Proper type1="h1" type2="c3" type3="c3" type4="h1" periodicity1="3" phase1="0.0" k1="0.6508444444444444"/>
    <Proper type1="h1" type2="c3" type3="oh" type4="ho" periodicity1="3" phase1="0.0" k1="0.6973333333333334"/>
    <Proper type1="h1" type2="c3" type3="c3" type4="h2" periodicity1="3" phase1="0.0" k1="0.6508444444444444"/>
    <Improper type1="c" type2="c3" type3="o" type4="o" periodicity1="2" phase1="3.141592653589793" k1="4.6024"/>
    <Improper type1="ca" type2="h5" type3="nb" type4="nb" periodicity1="2" phase1="3.141592653589793" k1="4.6024"/>
    <Improper type1="ca" type2="ca" type3="na" type4="nb" periodicity1="2" phase1="3.141592653589793" k1="4.6024"/>
    <Improper type1="ca" type2="ca" type3="ca" type4="nc" periodicity1="2" phase1="3.141592653589793" k1="4.6024"/>
    <Improper type1="ca" type2="ca" type3="nb" type4="nh" periodicity1="2" phase1="3.141592653589793" k1="4.6024"/>
    <Improper type1="nh" type2="ca" type3="hn" type4="hn" periodicity1="2" phase1="3.141592653589793" k1="4.6024"/>
    <Improper type1="cd" type2="h5" type3="na" type4="nc" periodicity1="2" phase1="3.141592653589793" k1="4.6024"/>
    <Improper type1="na" type2="c3" type3="ca" type4="cd" periodicity1="2" phase1="3.141592653589793" k1="4.6024"/>
  </PeriodicTorsionForce>
  <NonbondedForce coulomb14scale="0.8333333333333334" lj14scale="0.5">
    <UseAttributeFromResidue name="charge"/>
    <Atom type="n3" sigma="0.3249998523775958" epsilon="0.7112800000000001"/>
    <Atom type="c3" sigma="0.3399669508423535" epsilon="0.4577296"/>
    <Atom type="c" sigma="0.3399669508423535" epsilon="0.359824"/>
    <Atom type="o" sigma="0.2959921901149463" epsilon="0.87864"/>
    <Atom type="s4" sigma="0.35635948725613575" epsilon="1.046"/>
    <Atom type="os" sigma="0.3000012343465779" epsilon="0.7112800000000001"/>
    <Atom type="oh" sigma="0.3066473387839048" epsilon="0.8803136"/>
    <Atom type="nb" sigma="0.3249998523775958" epsilon="0.7112800000000001"/>
    <Atom type="ca" sigma="0.3399669508423535" epsilon="0.359824"/>
    <Atom type="nh" sigma="0.3249998523775958" epsilon="0.7112800000000001"/>
    <Atom type="nc" sigma="0.3249998523775958" epsilon="0.7112800000000001"/>
    <Atom type="cd" sigma="0.3399669508423535" epsilon="0.359824"/>
    <Atom type="na" sigma="0.3249998523775958" epsilon="0.7112800000000001"/>
    <Atom type="hn" sigma="0.10690784617684071" epsilon="0.06568879999999999"/>
    <Atom type="h1" sigma="0.2471353044121301" epsilon="0.06568879999999999"/>
    <Atom type="hc" sigma="0.2649532787749369" epsilon="0.06568879999999999"/>
    <Atom type="ho" sigma="1.0" epsilon="0.0"/>
    <Atom type="h2" sigma="0.22931733004932334" epsilon="0.06568879999999999"/>
    <Atom type="h5" sigma="0.24214627159054422" epsilon="0.06276"/>
  </NonbondedForce>
</ForceField>
